[
 {
  "id": 2,
  "start": 0,
  "end": 80,
  "label": "建立气腹",
  "index": 1,
  "updated_at": "2021-07-21 17:27:07"
 },
 {
  "id": 4,
  "start": 123,
  "end": 891,
  "label": "游离胆囊三角",
  "index": 2,
  "updated_at": "2021-07-21 17:27:07"
 },
 {
  "id": 5,
  "start": 892,
  "end": 1170,
  "label": "分离胆囊床",
  "index": 3,
  "updated_at": "2021-07-21 17:27:07"
 },
 {
  "id": 6,
  "start": 1181,
  "end": 1358,
  "label": "清理术野",
  "index": 4,
  "updated_at": "2021-07-21 17:27:07"
 },
 {
  "id": 1,
  "start": 1407,
  "end": 1474,
  "label": "抓取胆囊",
  "index": 5,
  "updated_at": "2021-07-21 17:27:07"
 }
]