[
 {
  "id": 2,
  "start": 0,
  "end": 102,
  "label": "建立气腹",
  "index": 1,
  "updated_at": "2021-07-12 20:20:27"
 },
 {
  "id": 4,
  "start": 256,
  "end": 676,
  "label": "游离胆囊三角",
  "index": 2,
  "updated_at": "2021-07-12 20:20:27"
 },
 {
  "id": 5,
  "start": 676,
  "end": 822,
  "label": "分离胆囊床",
  "index": 3,
  "updated_at": "2021-07-12 20:20:27"
 },
 {
  "id": 1,
  "start": 858,
  "end": 884,
  "label": "抓取胆囊",
  "index": 4,
  "updated_at": "2021-07-12 20:20:27"
 },
 {
  "id": 6,
  "start": 884,
  "end": 1240,
  "label": "清理术野",
  "index": 5,
  "updated_at": "2021-07-12 20:20:27"
 },
 {
  "id": 1,
  "start": 1291,
  "end": 1334,
  "label": "抓取胆囊",
  "index": 6,
  "updated_at": "2021-07-12 20:20:27"
 }
]