[
 {
  "id": 2,
  "start": 23.708082,
  "end": 70.166916,
  "label": "建立气腹",
  "index": 1,
  "updated_at": "2021-07-19 11:26:24"
 },
 {
  "id": 4,
  "start": 146.5425,
  "end": 651.180194,
  "label": "游离胆囊三角",
  "index": 2,
  "updated_at": "2021-07-19 11:26:24"
 },
 {
  "id": 5,
  "start": 666.677476,
  "end": 930.102386,
  "label": "分离胆囊床",
  "index": 3,
  "updated_at": "2021-07-19 11:26:24"
 },
 {
  "id": 6,
  "start": 935.593242,
  "end": 1069.216262,
  "label": "清理术区",
  "index": 4,
  "updated_at": "2021-07-19 11:26:24"
 },
 {
  "id": 1,
  "start": 1106.012504,
  "end": 1131.60317,
  "label": "取出胆囊",
  "index": 5,
  "updated_at": "2021-07-19 11:26:24"
 }
]