[
 {
  "id": 1,
  "start": 299.52,
  "end": 307.68,
  "label": "夹胆囊管",
  "index": 1,
  "updated_at": "2021-07-11 23:02:00"
 },
 {
  "id": 3,
  "start": 322.624042,
  "end": 350.883167,
  "label": "离断胆囊管",
  "index": 2,
  "updated_at": "2021-07-11 23:02:00"
 },
 {
  "id": 2,
  "start": 373.92,
  "end": 378.83825,
  "label": "夹胆囊动脉",
  "index": 3,
  "updated_at": "2021-07-11 23:02:00"
 },
 {
  "id": 2,
  "start": -1,
  "end": -1,
  "label": "夹胆囊动脉",
  "index": 4,
  "updated_at": "2021-07-11 23:02:00"
 },
 {
  "id": 4,
  "start": 391.160167,
  "end": 396.255959,
  "label": "离断胆囊动脉",
  "index": 5,
  "updated_at": "2021-07-11 23:02:00"
 }
]