[
 {
  "id": 1,
  "start": 323,
  "end": 345,
  "label": "夹胆囊管",
  "index": "0",
  "updated_at": "2021-07-25 21:45:15"
 },
 {
  "id": 1,
  "start": 357,
  "end": 365,
  "label": "夹胆囊管",
  "index": "1",
  "updated_at": "2021-07-25 21:45:15"
 },
 {
  "id": 3,
  "start": 370,
  "end": 389,
  "label": "离断胆囊管",
  "index": "2",
  "updated_at": "2021-07-25 21:45:15"
 },
 {
  "id": 2,
  "start": 400,
  "end": 407,
  "label": "夹胆囊动脉",
  "index": "3",
  "updated_at": "2021-07-25 21:45:15"
 },
 {
  "id": 4,
  "start": 416,
  "end": 419,
  "label": "离断胆囊动脉",
  "index": "4",
  "updated_at": "2021-07-25 21:45:15"
 },
 {
  "id": 2,
  "start": 528.173393,
  "end": 536.472631,
  "label": "夹胆囊动脉",
  "index": "41",
  "updated_at": "2021-07-25 21:45:15"
 },
 {
  "id": 4,
  "start": 544.524959,
  "end": 548.446389,
  "label": "离断胆囊动脉",
  "index": "411",
  "updated_at": "2021-07-25 21:45:15"
 }
]