[
 {
  "id": 1,
  "start": 867,
  "end": 877,
  "label": "夹胆囊管",
  "index": "0",
  "updated_at": "2021-07-21 20:43:47"
 },
 {
  "id": 1,
  "start": 896,
  "end": 904,
  "label": "夹胆囊管",
  "index": "1",
  "updated_at": "2021-07-21 20:43:47"
 },
 {
  "id": 1,
  "start": 916,
  "end": 925,
  "label": "夹胆囊管",
  "index": "2",
  "updated_at": "2021-07-21 20:43:47"
 },
 {
  "id": 1,
  "start": 935,
  "end": 960,
  "label": "夹胆囊管",
  "index": "3",
  "updated_at": "2021-07-21 20:43:47"
 },
 {
  "id": 3,
  "start": 966,
  "end": 979,
  "label": "离断胆囊管",
  "index": "4",
  "updated_at": "2021-07-21 20:43:47"
 }
]