[
 {
  "id": 1,
  "start": 522,
  "end": 532,
  "label": "夹胆囊管",
  "index": "0",
  "updated_at": "2021-07-24 20:53:55"
 },
 {
  "id": 1,
  "start": 545,
  "end": 554,
  "label": "夹胆囊管",
  "index": "1",
  "updated_at": "2021-07-24 20:53:55"
 },
 {
  "id": 1,
  "start": 568,
  "end": 578,
  "label": "夹胆囊管",
  "index": "2",
  "updated_at": "2021-07-24 20:53:55"
 },
 {
  "id": 3,
  "start": 586,
  "end": 594,
  "label": "离断胆囊管",
  "index": "3",
  "updated_at": "2021-07-24 20:53:55"
 },
 {
  "id": 2,
  "start": 631,
  "end": 640,
  "label": "夹胆囊动脉",
  "index": "4",
  "updated_at": "2021-07-24 20:53:55"
 },
 {
  "id": 4,
  "start": 652,
  "end": 657,
  "label": "离断胆囊动脉",
  "index": "5",
  "updated_at": "2021-07-24 20:53:55"
 }
]