[
 {
  "id": 2,
  "start": 986.434123,
  "end": 998.394339,
  "label": "夹胆囊动脉",
  "index": 1,
  "updated_at": "2021-07-25 00:14:18"
 },
 {
  "id": 4,
  "start": 1009.687169,
  "end": 1014.780425,
  "label": "离断胆囊动脉",
  "index": 2,
  "updated_at": "2021-07-25 00:14:18"
 },
 {
  "id": 1,
  "start": 1065.561669,
  "end": 1069.027981,
  "label": "夹胆囊管",
  "index": 3,
  "updated_at": "2021-07-25 00:14:18"
 },
 {
  "id": 1,
  "start": 1085.592487,
  "end": 1088.301531,
  "label": "夹胆囊管",
  "index": 4,
  "updated_at": "2021-07-25 00:14:18"
 },
 {
  "id": 1,
  "start": 1110.465571,
  "end": 1113.932035,
  "label": "夹胆囊管",
  "index": 5,
  "updated_at": "2021-07-25 00:14:18"
 },
 {
  "id": 3,
  "start": 1122.697709,
  "end": 1126.356337,
  "label": "离断胆囊管",
  "index": 6,
  "updated_at": "2021-07-25 00:14:18"
 }
]