[
 {
  "id": 1,
  "start": 354.315809,
  "end": 357.05824,
  "label": "夹胆囊管",
  "index": 1,
  "updated_at": "2021-07-24 22:28:02"
 },
 {
  "id": 1,
  "start": 361.846423,
  "end": 364.058917,
  "label": "夹胆囊管",
  "index": 2,
  "updated_at": "2021-07-24 22:28:02"
 },
 {
  "id": 3,
  "start": 383.742291,
  "end": 396.734276,
  "label": "离断胆囊管",
  "index": 3,
  "updated_at": "2021-07-24 22:28:02"
 },
 {
  "id": 2,
  "start": 427.790177,
  "end": 430.223241,
  "label": "夹胆囊动脉",
  "index": 4,
  "updated_at": "2021-07-24 22:28:02"
 },
 {
  "id": 4,
  "start": 438.297052,
  "end": 439.519925,
  "label": "离断胆囊动脉",
  "index": 5,
  "updated_at": "2021-07-24 22:28:02"
 }
]