[
 {
  "id": 2,
  "start": 77,
  "end": 197,
  "label": "建立气腹",
  "index": 1,
  "updated_at": "2021-07-31 23:47:46"
 },
 {
  "id": 5,
  "start": 1063,
  "end": 1361,
  "label": "分离胆囊床",
  "index": 3,
  "updated_at": "2021-07-31 23:47:46"
 },
 {
  "id": 6,
  "start": 1376,
  "end": 1546,
  "label": "清理术野",
  "index": 4,
  "updated_at": "2021-07-31 23:47:46"
 },
 {
  "id": 1,
  "start": 1564,
  "end": 1691,
  "label": "抓取胆囊",
  "index": 5,
  "updated_at": "2021-07-31 23:47:46"
 },
 {
  "id": 4,
  "start": 292,
  "end": 771.257928,
  "label": "游离胆囊三角",
  "index": 6,
  "updated_at": "2021-07-31 23:47:46"
 },
 {
  "id": 5,
  "start": 782.686913,
  "end": 821.071876,
  "label": "分离胆囊床",
  "index": 7,
  "updated_at": "2021-07-31 23:47:46"
 },
 {
  "id": 4,
  "start": 836.058254,
  "end": 891.224521,
  "label": "游离胆囊三角",
  "index": 8,
  "updated_at": "2021-07-31 23:47:46"
 },
 {
  "id": 5,
  "start": 891.224592,
  "end": 935.849287,
  "label": "分离胆囊床",
  "index": 9,
  "updated_at": "2021-07-31 23:47:46"
 },
 {
  "id": 4,
  "start": 952.424229,
  "end": 1039.049189,
  "label": "游离胆囊三角",
  "index": 10,
  "updated_at": "2021-07-31 23:47:46"
 }
]