[
 {
  "id": 2,
  "start": 10.054628,
  "end": 91.87783,
  "label": "建立气腹",
  "index": 1,
  "updated_at": "2021-07-18 14:27:17"
 },
 {
  "id": 4,
  "start": 273.603103,
  "end": 622.156587,
  "label": "游离胆囊三角",
  "index": 2,
  "updated_at": "2021-07-18 14:27:17"
 },
 {
  "id": 5,
  "start": 624.359725,
  "end": 742.256739,
  "label": "分离胆囊床",
  "index": 3,
  "updated_at": "2021-07-18 14:27:17"
 },
 {
  "id": 4,
  "start": 763.399251,
  "end": 854.967647,
  "label": "游离胆囊三角",
  "index": 4,
  "updated_at": "2021-07-18 14:27:17"
 },
 {
  "id": 5,
  "start": 870.097959,
  "end": 1014.767383,
  "label": "分离胆囊床",
  "index": 5,
  "updated_at": "2021-07-18 14:27:17"
 },
 {
  "id": 1,
  "start": 1033.129109,
  "end": 1072.910483,
  "label": "取出胆囊",
  "index": 6,
  "updated_at": "2021-07-18 14:27:17"
 },
 {
  "id": 6,
  "start": 1085.329263,
  "end": 1329.569281,
  "label": "清理术区",
  "index": 7,
  "updated_at": "2021-07-18 14:27:17"
 },
 {
  "id": 1,
  "start": 1340.624779,
  "end": 1541.330425,
  "label": "取出胆囊",
  "index": 8,
  "updated_at": "2021-07-18 14:27:17"
 },
 {
  "id": 6,
  "start": 1667.599339,
  "end": 1690.608403,
  "label": "清理术区",
  "index": 9,
  "updated_at": "2021-07-18 14:27:17"
 }
]