[
  {
    "id": 2,
    "start": 252,
    "end": 377,
    "label": "建立气腹",
    "index": 1,
    "updated_at": "2021-07-11 16:14:43"
  },
  {
    "id": 4,
    "start": 436,
    "end": 900,
    "label": "游离胆囊三角",
    "index": 2,
    "updated_at": "2021-07-11 16:14:43"
  },
  {
    "id": 5,
    "start": 900,
    "end": 1001,
    "label": "分离胆囊床",
    "index": 3,
    "updated_at": "2021-07-11 16:14:43"
  },
  {
    "id": 4,
    "start": 1001,
    "end": 1108,
    "label": "游离胆囊三角",
    "index": 4,
    "updated_at": "2021-07-11 16:14:43"
  },
  {
    "id": 5,
    "start": 1136,
    "end": 1253,
    "label": "分离胆囊床",
    "index": 5,
    "updated_at": "2021-07-11 16:14:43"
  },
  {
    "id": 6,
    "start": 1267,
    "end": 1478,
    "label": "清理术野",
    "index": 6,
    "updated_at": "2021-07-11 16:14:43"
  },
  {
    "id": 1,
    "start": 1492,
    "end": 2044,
    "label": "抓取胆囊",
    "index": 7,
    "updated_at": "2021-07-11 16:14:43"
  }
]